<?xml version = '1.0' encoding = 'UTF-8'?>
<Diagram class="oracle.dbtools.crest.swingui.relational.DPVRelational" name="Relational_1" id="A051A165-3E48-EF51-3769-7513BED5B272">
<createdBy>Vlad</createdBy>
<modifiedBy>Vlad</modifiedBy>
<createdTime>2020-11-01 08:54:14 UTC</createdTime>
<autoRoute>false</autoRoute>
<boxInbox>true</boxInbox>
<showLegend>false</showLegend>
<showLabels>true</showLabels>
<showRelAttributes>false</showRelAttributes>
<gridEnabled>false</gridEnabled>
<showGrid>false</showGrid>
<diagramColor>-1</diagramColor>
<display>false</display>
<notation>1</notation>
<objectViews>
<OView class="oracle.dbtools.crest.swingui.relational.TVTable" oid="2EED3B93-782D-E68F-0A9B-78015A81E565" otype="Table" vid="F7EE899C-9975-8CAA-5D2B-10FB4720CE69">
<hideElementsInCurrentOnly>false</hideElementsInCurrentOnly>
<bounds x="78" y="74" width="241" height="212"/>
</OView>
<OView class="oracle.dbtools.crest.swingui.relational.TVTable" oid="4D399377-AEF6-0732-E2A2-E58AE476D6FB" otype="Table" vid="3D85201E-EB1B-BD29-B4A7-AEB601C4D35A">
<hideElementsInCurrentOnly>false</hideElementsInCurrentOnly>
<bounds x="531" y="405" width="239" height="164"/>
</OView>
<OView class="oracle.dbtools.crest.swingui.relational.TVTable" oid="5BCAF971-C256-78D9-4BE1-FE9529EB2683" otype="Table" vid="CAB59389-B330-1716-528B-4F1505A25592">
<hideElementsInCurrentOnly>false</hideElementsInCurrentOnly>
<bounds x="545" y="113" width="206" height="136"/>
</OView>
<OView class="oracle.dbtools.crest.swingui.relational.TVTable" oid="648167A4-FC98-028E-3805-D2B7CB0FA73A" otype="Table" vid="02610DC1-3CF7-7DCF-254E-755C2FAE4BE4">
<hideElementsInCurrentOnly>false</hideElementsInCurrentOnly>
<bounds x="988" y="375" width="243" height="226"/>
</OView>
<OView class="oracle.dbtools.crest.swingui.relational.TVTable" oid="9B062801-33BE-37BA-9CEB-287EF79A973D" otype="Table" vid="101F6F8E-D3BC-8E49-D64F-B27E18248798">
<hideElementsInCurrentOnly>false</hideElementsInCurrentOnly>
<bounds x="986" y="707" width="281" height="102"/>
</OView>
<OView class="oracle.dbtools.crest.swingui.relational.TVTable" oid="F764469E-3591-9D8C-8F9E-5697B562DDC8" otype="Table" vid="603430A8-3CB5-3676-2EF7-6304DD4A86B1">
<hideElementsInCurrentOnly>false</hideElementsInCurrentOnly>
<bounds x="124" y="446" width="212" height="144"/>
</OView>
</objectViews>
<connectors>
<Connector class="oracle.dbtools.crest.swingui.relational.TVFKRelation" oid="0E6F013A-7203-058A-52F8-D8284CE6950E" otype="FKIndexAssociation" vid_source="CAB59389-B330-1716-528B-4F1505A25592" vid_target="02610DC1-3CF7-7DCF-254E-755C2FAE4BE4">
<hideElementsInCurrentOnly>false</hideElementsInCurrentOnly>
<backgroundColor>-16777216</backgroundColor>
<lineWidth>1</lineWidth>
<centerLabel class="oracle.dbtools.crest.model.design.Label">
<site>1</site>
<labelBounds x="-77" y="-16" width="152" height="30"/>
<noBackgroundColor>true</noBackgroundColor>
<noForegroundColor>true</noForegroundColor>
</centerLabel>
<points>
<point x="750" y="249"/>
<point x="988" y="407"/>
</points>
</Connector>
<Connector class="oracle.dbtools.crest.swingui.relational.TVFKRelation" oid="2A855A46-938C-D4FB-97C0-E0571DD852CE" otype="FKIndexAssociation" vid_source="603430A8-3CB5-3676-2EF7-6304DD4A86B1" vid_target="3D85201E-EB1B-BD29-B4A7-AEB601C4D35A">
<hideElementsInCurrentOnly>false</hideElementsInCurrentOnly>
<backgroundColor>-16777216</backgroundColor>
<lineWidth>1</lineWidth>
<centerLabel class="oracle.dbtools.crest.model.design.Label">
<site>1</site>
<labelBounds x="-61" y="-16" width="120" height="30"/>
<noBackgroundColor>true</noBackgroundColor>
<noForegroundColor>true</noForegroundColor>
</centerLabel>
<points>
<point x="336" y="507"/>
<point x="531" y="507"/>
</points>
</Connector>
<Connector class="oracle.dbtools.crest.swingui.relational.TVFKRelation" oid="CAC98E0C-82A8-804C-8748-6554B95C198B" otype="FKIndexAssociation" vid_source="101F6F8E-D3BC-8E49-D64F-B27E18248798" vid_target="02610DC1-3CF7-7DCF-254E-755C2FAE4BE4">
<hideElementsInCurrentOnly>false</hideElementsInCurrentOnly>
<backgroundColor>-16777216</backgroundColor>
<lineWidth>1</lineWidth>
<centerLabel class="oracle.dbtools.crest.model.design.Label">
<site>1</site>
<labelBounds x="-79" y="-16" width="157" height="30"/>
<noBackgroundColor>true</noBackgroundColor>
<noForegroundColor>true</noForegroundColor>
</centerLabel>
<points>
<point x="1109" y="707"/>
<point x="1109" y="601"/>
</points>
</Connector>
<Connector class="oracle.dbtools.crest.swingui.relational.TVFKRelation" oid="DAB23E24-6756-3955-F65B-328859CDA91D" otype="FKIndexAssociation" vid_source="603430A8-3CB5-3676-2EF7-6304DD4A86B1" vid_target="F7EE899C-9975-8CAA-5D2B-10FB4720CE69">
<hideElementsInCurrentOnly>false</hideElementsInCurrentOnly>
<backgroundColor>-16777216</backgroundColor>
<lineWidth>1</lineWidth>
<centerLabel class="oracle.dbtools.crest.model.design.Label">
<site>1</site>
<labelBounds x="-91" y="-16" width="180" height="30"/>
<noBackgroundColor>true</noBackgroundColor>
<noForegroundColor>true</noForegroundColor>
</centerLabel>
<points>
<point x="221" y="446"/>
<point x="221" y="286"/>
</points>
</Connector>
<Connector class="oracle.dbtools.crest.swingui.relational.TVFKRelation" oid="DC1A255D-C557-B1CF-B42E-91FDC22F7C3A" otype="FKIndexAssociation" vid_source="603430A8-3CB5-3676-2EF7-6304DD4A86B1" vid_target="CAB59389-B330-1716-528B-4F1505A25592">
<hideElementsInCurrentOnly>false</hideElementsInCurrentOnly>
<backgroundColor>-16777216</backgroundColor>
<lineWidth>1</lineWidth>
<centerLabel class="oracle.dbtools.crest.model.design.Label">
<site>1</site>
<labelBounds x="-56" y="-16" width="111" height="30"/>
<noBackgroundColor>true</noBackgroundColor>
<noForegroundColor>true</noForegroundColor>
</centerLabel>
<points>
<point x="319" y="446"/>
<point x="563" y="249"/>
</points>
</Connector>
<Connector class="oracle.dbtools.crest.swingui.relational.TVFKRelation" oid="F505C29C-3E0B-B881-7471-8DCF88337770" otype="FKIndexAssociation" vid_source="3D85201E-EB1B-BD29-B4A7-AEB601C4D35A" vid_target="02610DC1-3CF7-7DCF-254E-755C2FAE4BE4">
<hideElementsInCurrentOnly>false</hideElementsInCurrentOnly>
<backgroundColor>-16777216</backgroundColor>
<lineWidth>1</lineWidth>
<centerLabel class="oracle.dbtools.crest.model.design.Label">
<site>1</site>
<labelBounds x="-81" y="-16" width="161" height="30"/>
<noBackgroundColor>true</noBackgroundColor>
<noForegroundColor>true</noForegroundColor>
</centerLabel>
<points>
<point x="770" y="487"/>
<point x="988" y="487"/>
</points>
</Connector>
</connectors>
</Diagram>
